setup.py
triop/Binomialdistribution.py
triop/Gaussiandistribution.py
triop/Generaldistribution.py
triop/__init__.py
triop.egg-info/PKG-INFO
triop.egg-info/SOURCES.txt
triop.egg-info/dependency_links.txt
triop.egg-info/not-zip-safe
triop.egg-info/top_level.txt