Metadata-Version: 1.0
Name: triop
Version: 0.112
Summary: Gaussian distributions
Home-page: UNKNOWN
Author: Vishesh Jain
Author-email: UNKNOWN
License: UNKNOWN
Platform: UNKNOWN
